README.txt
setup.py
modules/__init__.py
modules/ngdaemon.py
modules/nginit.py
modules/nglog.py
modules/ngreport.py
modules/ngrrd.py
modules/ngsubprocess.py
modules/ngyaml.py
ng_mini.egg-info/PKG-INFO
ng_mini.egg-info/SOURCES.txt
ng_mini.egg-info/dependency_links.txt
ng_mini.egg-info/top_level.txt