Metadata-Version: 1.1
Name: ng-mini
Version: 0.1.0
Summary: UNKNOWN
Home-page: http://www.chenqing.org
Author: qing.chen
Author-email: UNKNOWN
License: UNKNOWN
Platform: UNKNOWN
Requires: bottle
Requires: PyYAML
